indra/__init__.py
indra/conftest.py
indra/api/__init__.py
indra/api/api.cpython-311-darwin.so
indra/pytorch/__init__.py
indra/pytorch/buffered_loader.py
indra/pytorch/common.py
indra/pytorch/exceptions.py
indra/pytorch/loader.py
indra/pytorch/log.py
indra/pytorch/multi_processing_iterator.py
indra/pytorch/multiprocess_utils.py
indra/pytorch/single_process_iterator.py
indra/pytorch/tensorinfo.py
indra/pytorch/util.py
indra/tests/__init__.py
indra/tests/constants.py
indra/tests/dataset_fixtures.py
indra/tests/nifti_test.py
indra/tests/test_data.py
indra/tests/test_exceptions.py
indra/tests/test_indra_dataset.py
indra/tests/test_info.py
indra/tests/test_loader.py
indra/tests/test_materialize.py
indra/tests/test_queries.py
indra/tests/test_sampling.py
indra/tests/test_shape.py
indra/tests/test_slicing.py
indra/tests/test_tensors.py
indra/tests/test_version_control.py
indra/tests/test_writer.py
indra/tests/utils.py
libdeeplake-0.0.164.dist-info/METADATA
libdeeplake-0.0.164.dist-info/WHEEL
libdeeplake-0.0.164.dist-info/top_level.txt
libdeeplake-0.0.164.dist-info/RECORD
