Metadata-Version: 2.4
Name: libdeeplake
Version: 0.0.164
Summary: C++ backend for Deep Lake
Author: activeloop.ai
Author-email: support@activeloop.ai
Project-URL: Documentation, https://docs.activeloop.ai/
Project-URL: Source, https://github.com/activeloopai/indra
Requires-Dist: numpy
Requires-Dist: dill
Dynamic: author
Dynamic: author-email
Dynamic: description-content-type
Dynamic: project-url
Dynamic: requires-dist
Dynamic: summary
